Metadata-Version: 2.1
Name: dash-gif-component
Version: 1.1.0
Summary: Dash plugin for playable gifs
Home-page: https://github.com/mbkupfer/dash-gif-component.git
Author: Maxim Kupfer
Author-email: mbkupfer@gmail.com
License: MIT
Platform: UNKNOWN
